[
    {
        "id": "0",
        "name": "髙田知季",
        "bt": "右左"
    },
    {
        "id": "00",
        "name": "川瀬晃",
        "bt": "右左"
    },
    {
        "id": "1",
        "name": "内川聖一",
        "bt": "右右"
    },
    {
        "id": "4",
        "name": "バレンティン",
        "bt": "右右"
    },
    {
        "id": "5",
        "name": "松田宣浩",
        "bt": "右右"
    },
    {
        "id": "6",
        "name": "今宮健太",
        "bt": "右右"
    },
    {
        "id": "7",
        "name": "中村晃",
        "bt": "左左"
    },
    {
        "id": "8",
        "name": "明石健志",
        "bt": "右左"
    },
    {
        "id": "9",
        "name": "柳田悠岐",
        "bt": "右左"
    },
    {
        "id": "12",
        "name": "髙谷裕亮",
        "bt": "右左"
    },
    {
        "id": "19",
        "name": "甲斐拓也",
        "bt": "右右"
    },
    {
        "id": "22",
        "name": "西田哲朗",
        "bt": "右右"
    },
    {
        "id": "23",
        "name": "周東佑京",
        "bt": "右左"
    },
    {
        "id": "24",
        "name": "長谷川勇也",
        "bt": "右左"
    },
    {
        "id": "27",
        "name": "グラシアル",
        "bt": "右右"
    },
    {
        "id": "30",
        "name": "佐藤直樹",
        "bt": "右右"
    },
    {
        "id": "31",
        "name": "栗原陵矢",
        "bt": "右左"
    },
    {
        "id": "32",
        "name": "柳町達",
        "bt": "右左"
    },
    {
        "id": "33",
        "name": "増田珠",
        "bt": "右右"
    },
    {
        "id": "36",
        "name": "牧原大成",
        "bt": "右左"
    },
    {
        "id": "45",
        "name": "谷川原健太",
        "bt": "右左"
    },
    {
        "id": "46",
        "name": "コラス",
        "bt": "左左"
    },
    {
        "id": "51",
        "name": "上林誠知",
        "bt": "右左"
    },
    {
        "id": "52",
        "name": "リチャード",
        "bt": "右右"
    },
    {
        "id": "54",
        "name": "デスパイネ",
        "bt": "右右"
    },
    {
        "id": "55",
        "name": "野村大樹",
        "bt": "右右"
    },
    {
        "id": "59",
        "name": "水谷瞬",
        "bt": "右右"
    },
    {
        "id": "60",
        "name": "釜元豪",
        "bt": "右左"
    },
    {
        "id": "62",
        "name": "海野隆司",
        "bt": "右右"
    },
    {
        "id": "64",
        "name": "真砂勇介",
        "bt": "右右"
    },
    {
        "id": "65",
        "name": "九鬼隆平",
        "bt": "右右"
    },
    {
        "id": "68",
        "name": "三森大貴",
        "bt": "右左"
    },
    {
        "id": "69",
        "name": "小林珠維",
        "bt": "右右"
    },
    {
        "id": "99",
        "name": "川島慶三",
        "bt": "右右"
    },
    {
        "id": "121",
        "name": "石塚綜一郎",
        "bt": "右右"
    },
    {
        "id": "124",
        "name": "古澤勝吾",
        "bt": "右右"
    },
    {
        "id": "125",
        "name": "大本将吾",
        "bt": "右左"
    },
    {
        "id": "126",
        "name": "黒瀬健太",
        "bt": "右右"
    },
    {
        "id": "128",
        "name": "伊藤大将",
        "bt": "右右"
    },
    {
        "id": "130",
        "name": "勝連大稀",
        "bt": "右左"
    },
    {
        "id": "131",
        "name": "舟越秀虎",
        "bt": "右右"
    },
    {
        "id": "132",
        "name": "渡邉陸",
        "bt": "右左"
    },
    {
        "id": "135",
        "name": "田城飛翔",
        "bt": "右左"
    },
    {
        "id": "136",
        "name": "荒木翔太",
        "bt": "右右"
    },
    {
        "id": "139",
        "name": "日暮矢麻人",
        "bt": "左左"
    },
    {
        "id": "141",
        "name": "清水陸哉",
        "bt": "右右"
    },
    {
        "id": "142",
        "name": "中村宜聖",
        "bt": "右右"
    },
    {
        "id": "144",
        "name": "堀内汰門",
        "bt": "右右"
    }
]